purenv/purenv.py
purenv-0.1.0.dist-info/METADATA
purenv-0.1.0.dist-info/WHEEL
purenv-0.1.0.dist-info/top_level.txt
purenv-0.1.0.dist-info/RECORD
